extractcode_7z/__init__.py
extractcode_7z/__pycache__/__init__.cpython-312-pytest-8.3.3.pyc
extractcode_7z_system_provided-33.0.1.dist-info/LICENSE.txt
extractcode_7z_system_provided-33.0.1.dist-info/METADATA
extractcode_7z_system_provided-33.0.1.dist-info/README.rst
extractcode_7z_system_provided-33.0.1.dist-info/WHEEL
extractcode_7z_system_provided-33.0.1.dist-info/apache-2.0.LICENSE
extractcode_7z_system_provided-33.0.1.dist-info/entry_points.txt
extractcode_7z_system_provided-33.0.1.dist-info/top_level.txt
extractcode_7z_system_provided-33.0.1.dist-info/RECORD
