Metadata-Version: 2.1
Name: extractcode_7z_system_provided
Version: 33.0.1
Summary: A ScanCode path provider plugin to provide system package provided sevenzip binary.
Home-page: https://github.com/aboutcode-org/scancode-plugins
Author: nexB
Author-email: info@aboutcode.org
License: apache-2.0 AND lgpl-2.1 and unrar and brian-gladman-3-clause
Keywords: open source,extractcode,libarchive
Classifier: Development Status :: 5 - Production/Stable
Classifier: Intended Audience :: Developers
Classifier: Topic :: Utilities
License-File: LICENSE.txt
License-File: README.rst
License-File: apache-2.0.LICENSE
